wallarm_api/__init__.py
wallarm_api/wallarm_api.py
wallarm_api/core/__init__.py
wallarm_api/core/api/__init__.py
wallarm_api/core/api/attacks_api.py
wallarm_api/core/api/audit_log_api.py
wallarm_api/core/api/base_api.py
wallarm_api/core/api/billing_api.py
wallarm_api/core/api/clients_api.py
wallarm_api/core/api/graph_api.py
wallarm_api/core/api/hints_api.py
wallarm_api/core/api/integrations_api.py
wallarm_api/core/api/node_api.py
wallarm_api/core/api/triggers_api.py
wallarm_api/core/api/users_api.py
wallarm_api/core/api/vulnerabilities_api.py
wallarm_api/core/clients/__init__.py
wallarm_api/core/clients/bare_http_client.py
wallarm_api/core/clients/response_handler.py
wallarm_api/core/clients/errors/__init__.py
wallarm_api/core/clients/errors/http_errors.py
wallarm_api/core/enums/__init__.py
wallarm_api/core/enums/action.py
wallarm_api/core/enums/component.py
wallarm_api/core/enums/language.py
wallarm_api/core/enums/object_type.py
wallarm_api/core/enums/role.py
wallarm_api/core/models/__init__.py
wallarm_api/core/models/attack.py
wallarm_api/core/models/audit_log.py
wallarm_api/core/models/billing.py
wallarm_api/core/models/client.py
wallarm_api/core/models/dashboard.py
wallarm_api/core/models/graph_data.py
wallarm_api/core/models/hint.py
wallarm_api/core/models/integration.py
wallarm_api/core/models/node.py
wallarm_api/core/models/trigger.py
wallarm_api/core/models/user.py
wallarm_api/core/models/vulnerability.py
wallarm_api-0.17.dist-info/LICENSE.txt
wallarm_api-0.17.dist-info/METADATA
wallarm_api-0.17.dist-info/WHEEL
wallarm_api-0.17.dist-info/top_level.txt
wallarm_api-0.17.dist-info/RECORD
